youtube_summary/__init__.py
youtube_summary/__main__.py
youtube_summary/main.py
youtube_summary/overall_summarizer.py
youtube_summary/section_summarizer.py
youtube_summary/transcript.py
youtube_summary/video_infromation.py
youtube_summary-0.5.dist-info/LICENSE
youtube_summary-0.5.dist-info/METADATA
youtube_summary-0.5.dist-info/WHEEL
youtube_summary-0.5.dist-info/entry_points.txt
youtube_summary-0.5.dist-info/top_level.txt
youtube_summary-0.5.dist-info/RECORD
